setup.py
directional_parity/__init__.py
directional_parity/decoder.py
directional_parity/encoder.py
directional_parity/errors.py
directional_parity/temperature.py
directional_parity.egg-info/PKG-INFO
directional_parity.egg-info/SOURCES.txt
directional_parity.egg-info/dependency_links.txt
directional_parity.egg-info/top_level.txt
directional_parity.egg-info/zip-safe
scripts/directional_parity_decode
scripts/directional_parity_encode
scripts/wnyc_cicada_decode_temp