Metadata-Version: 1.0
Name: directional-parity
Version: 0.0.0
Summary: Direction detecting parity - developed for project.wnyc.org/cicadas
Home-page: https://github.com/adamdeprince/wnyc_systems
Author: Adam DePrince
Author-email: adeprince@nypublicradio.org
License: UNKNOWN
Platform: UNKNOWN
